struct2args/__init__.py
struct2args/_util.py
struct2args/cli.py
struct2args/generate.py
struct2args-0.1.1.dist-info/METADATA
struct2args-0.1.1.dist-info/WHEEL
struct2args-0.1.1.dist-info/entry_points.txt
struct2args-0.1.1.dist-info/RECORD
